wangeditor/__init__.py
wangeditor/configs.py
wangeditor/fields.py
wangeditor/urls.py
wangeditor/utils.py
wangeditor/views.py
wangeditor/widgets.py
wangeditor/backends/__init__.py
wangeditor/backends/dummy_backend.py
wangeditor/static/wangeditor/wangEditor-v5.js
wangeditor/static/wangeditor/wangEditor-v5.js.map
wangeditor/static/wangeditor/wangeditor-init.js
wangeditor/static/wangeditor/css/style.css
wangeditor/templates/wangeditor/widget.html
django_wangeditor-2.0.0.dist-info/LICENSE
django_wangeditor-2.0.0.dist-info/METADATA
django_wangeditor-2.0.0.dist-info/WHEEL
django_wangeditor-2.0.0.dist-info/top_level.txt
django_wangeditor-2.0.0.dist-info/RECORD
